AUTHORS.rst
CONTRIBUTING.rst
HISTORY.rst
LICENSE
MANIFEST.in
README.rst
requirements.txt
setup.py
django_templation.egg-info/PKG-INFO
django_templation.egg-info/SOURCES.txt
django_templation.egg-info/dependency_links.txt
django_templation.egg-info/not-zip-safe
django_templation.egg-info/requires.txt
django_templation.egg-info/top_level.txt
templation/__init__.py
templation/admin.py
templation/context_processor.py
templation/loaders.py
templation/locals.py
templation/middleware.py
templation/models.py
templation/settings.py
templation/urls.py
templation/utils.py
templation/views.py
templation/templatetags/__init__.py
templation/templatetags/templation_tags.py