Metadata-Version: 1.1
Name: django-templation
Version: 0.1.0
Summary: The easy way to allow designers edit templates and assets.
Home-page: https://github.com/qdqmedia/django-templation
Author: QDQ media S.A.U.
Author-email: tecnologia@qdqmedia.com
License: BSD
Keywords: django-templation
Platform: UNKNOWN
Classifier: Development Status :: 2 - Pre-Alpha
Classifier: Framework :: Django
Classifier: Intended Audience :: Developers
Classifier: License :: OSI Approved :: BSD License
Classifier: Natural Language :: English
Classifier: Programming Language :: Python :: 2
Classifier: Programming Language :: Python :: 2.6
Classifier: Programming Language :: Python :: 2.7
Classifier: Programming Language :: Python :: 3
Classifier: Programming Language :: Python :: 3.3
